commonroad_sumo/__init__.py
commonroad_sumo/backend/__init__.py
commonroad_sumo/backend/mock_sumo_simulation_backend.py
commonroad_sumo/backend/sumo_simulation_backend.py
commonroad_sumo/backend/types.py
commonroad_sumo/cr2sumo/__init__.py
commonroad_sumo/cr2sumo/map_converter/__init__.py
commonroad_sumo/cr2sumo/map_converter/intersections.py
commonroad_sumo/cr2sumo/map_converter/lanelets.py
commonroad_sumo/cr2sumo/map_converter/map_converter.py
commonroad_sumo/cr2sumo/map_converter/mapping.py
commonroad_sumo/cr2sumo/map_converter/templates/DEU.typ.xml
commonroad_sumo/cr2sumo/map_converter/templates/README.md
commonroad_sumo/cr2sumo/map_converter/templates/USA.typ.xml
commonroad_sumo/cr2sumo/map_converter/templates/ZAM.typ.xml
commonroad_sumo/cr2sumo/map_converter/templates/default.sumo.cfg
commonroad_sumo/cr2sumo/map_converter/traffic_light.py
commonroad_sumo/cr2sumo/map_converter/traffic_sign.py
commonroad_sumo/cr2sumo/map_converter/util.py
commonroad_sumo/cr2sumo/traffic_generator/__init__.py
commonroad_sumo/cr2sumo/traffic_generator/demand_calculator.py
commonroad_sumo/cr2sumo/traffic_generator/flow_traffic_generator.py
commonroad_sumo/cr2sumo/traffic_generator/random_trips_traffic_generator.py
commonroad_sumo/cr2sumo/traffic_generator/sumo_map_matcher.py
commonroad_sumo/cr2sumo/traffic_generator/traffic_generator.py
commonroad_sumo/cr2sumo/traffic_generator/trajectory_traffic_generator.py
commonroad_sumo/errors.py
commonroad_sumo/helpers.py
commonroad_sumo/interface/__init__.py
commonroad_sumo/interface/driving_model_parameters_provider.py
commonroad_sumo/interface/id_mapper.py
commonroad_sumo/interface/interfaces/__init__.py
commonroad_sumo/interface/interfaces/base_interface.py
commonroad_sumo/interface/interfaces/dynamic_obstacle_interface.py
commonroad_sumo/interface/interfaces/pedestrian_interface.py
commonroad_sumo/interface/interfaces/traffic_light_interface.py
commonroad_sumo/interface/interfaces/vehicle_interface.py
commonroad_sumo-2025.1.4.dist-info/METADATA
commonroad_sumo-2025.1.4.dist-info/WHEEL
commonroad_sumo-2025.1.4.dist-info/licenses/LICENSE.txt
commonroad_sumo-2025.1.4.dist-info/RECORD
