Metadata-Version: 2.4
Name: commonroad-sumo
Version: 2025.1.4
Summary: Interface between CommonRoad and the SUMO traffic simulator
License-Expression: BSD-3-Clause
License-File: LICENSE.txt
Author: Florian Finkeldei
Author-email: florian.finkeldei@tum.de
Requires-Python: >=3.10,<4.0
Classifier: Programming Language :: Python :: 3
Classifier: Programming Language :: Python :: 3.10
Classifier: Programming Language :: Python :: 3.11
Classifier: Programming Language :: Python :: 3.12
Classifier: Programming Language :: Python :: 3.13
Classifier: Programming Language :: Python :: 3.14
Provides-Extra: dev
Provides-Extra: docs
Provides-Extra: test
Requires-Dist: commonroad-io (>=2024.3,<2025.0)
Requires-Dist: coverage[toml] (>=7.5,<8.0.0) ; extra == "test"
Requires-Dist: ffmpeg (>=1.4,<2.0.0)
Requires-Dist: libsumo (>=1.24.0,<2.0.0)
Requires-Dist: matplotlib (>=3.0.0,<4.0.0)
Requires-Dist: mkdocs (>=1.6.0,<2.0.0) ; extra == "docs"
Requires-Dist: mkdocs-autorefs (>=1.0.1,<2.0.0) ; extra == "docs"
Requires-Dist: mkdocs-material (>=9.6.14,<10.0.0) ; extra == "docs"
Requires-Dist: mkdocstrings-python (>=1.10.3,<2.0.0) ; extra == "docs"
Requires-Dist: numpy (>=1.26.1) ; python_version < "3.13"
Requires-Dist: numpy (>=2.1.0) ; python_version >= "3.13"
Requires-Dist: parameterized (>=0.8.1,<1.0.0) ; extra == "test"
Requires-Dist: pre-commit (>=3.5.0,<4.0.0) ; extra == "dev"
Requires-Dist: pytest (>=7.4,<8.0.0) ; extra == "test"
Requires-Dist: pytest-mock (>=3.12.0,<4.0.0) ; extra == "test"
Requires-Dist: shapely (>=2.0.0,<3.0.0)
Requires-Dist: traci (>=1.24.0,<2.0.0)
Requires-Dist: typing-extensions (>=4.12.2,<5.0.0)
Project-URL: Documentation, https://cps.pages.gitlab.lrz.de/sumo-interface/
